infrared_ospdui-3.0.0.dist-info/DESCRIPTION.rst
infrared_ospdui-3.0.0.dist-info/METADATA
infrared_ospdui-3.0.0.dist-info/RECORD
infrared_ospdui-3.0.0.dist-info/WHEEL
infrared_ospdui-3.0.0.dist-info/entry_points.txt
infrared_ospdui-3.0.0.dist-info/metadata.json
infrared_ospdui-3.0.0.dist-info/pbr.json
infrared_ospdui-3.0.0.dist-info/top_level.txt
ospdui/__init__.py
ospdui/main.yml
ospdui/plugin.spec
ospdui/release.yml
ospdui/run.yml
ospdui/setup.yml
ospdui/vnc.yml
ospdui/roles/vnc-server/defaults/main.yml
ospdui/roles/vnc-server/tasks/main.yml
ospdui/roles/vnc-server/templates/vncserver.service.j2
ospdui/tasks/environment.yml
ospdui/tasks/network.yml
ospdui/tasks/repo.yml
ospdui/tasks/selenium.yml
ospdui/templates/ifcfg.conf.j2
ospdui/templates/ospduiTests.conf.json.j2
ospdui/vars/setup/default.yml
ospdui/vars/setup/master.yml
ospdui/vars/topology/config/default.conf
